{
	"assessment": [
		{
			"name": "Crystal structure",
			"weight": 5
		},
		{
			"name": "Diffraction",
			"weight": 5
		},
		{
			"name": "Index of electron diffraction patterns",
			"weight": 5
		},
		{
			"name": "Quiz",
			"weight": 10
		},
		{
			"name": "Crystal Structure Modelling",
			"weight": 5
		},
		{
			"name": "Experimental Design of Materials Characterisation",
			"weight": 20
		},
		{
			"name": "X-ray Photoelectron Spectroscopy/Fluorescence",
			"weight": 5
		},
		{
			"name": "Materials characterisation",
			"weight": 25
		},
		{
			"name": "Final exam",
			"weight": 20
		}
	]
}