{
	"assessment": [
		{
			"name": "Online Quiz 1 AT HOME - via Blackboard",
			"weight": 10
		},
		{
			"name": "Online Quiz 2 AT HOME - via Black - via Blackboard",
			"weight": 10
		},
		{
			"name": "Online Quiz 3 in LECTURE - via Blackboard",
			"weight": 20
		},
		{
			"name": "Module I Critical Thinking Exercise",
			"weight": 20
		},
		{
			"name": "Module II Criticial Thinking Exercise",
			"weight": 20
		},
		{
			"name": "Module III Criticial Thinking Exercise",
			"weight": 20
		}
	]
}