{
	"assessment": [
		{
			"name": "Work Health and Safety & Cultural Safety Modules",
			"weight": "NGP"
		},
		{
			"name": "Hand Hygiene, Infection Control & MH Competencies",
			"weight": "NGP"
		},
		{
			"name": "Medication online learning and quizzes",
			"weight": "NGP"
		},
		{
			"name": "Objective Structured Clinical Skills Assessment",
			"weight": "NGP"
		},
		{
			"name": "ANSAT - Formative and Summative",
			"weight": "NGP"
		},
		{
			"name": "Objective Structured Clinical Skills Assessment",
			"weight": "NGP"
		}
	]
}